{"XMLLevel": {"@CollectableMonster": "", "@HideCallout": "-1", "@LettersGroup": "1", "@SegmentTime": "11", "@StoneType": "1", "@monsterInputType": "Letter", "Segments": {"Segment": [{"@SegmentTime": "11", "@spawnIds": "82,83", "MonsterRequiredLetters": {"string": "t"}, "MonsterAllLetters": null, "Stones": {"string": ["g", "t"]}}, {"@SegmentTime": "11", "@spawnIds": "21,22", "MonsterRequiredLetters": {"string": "g"}, "MonsterAllLetters": null, "Stones": {"string": ["t", "g"]}}, {"@SegmentTime": "11", "@spawnIds": "93,94", "MonsterRequiredLetters": {"string": "b"}, "MonsterAllLetters": null, "Stones": {"string": ["t", "b"]}}, {"@SegmentTime": "11", "@spawnIds": "54,55", "MonsterRequiredLetters": {"string": "b"}, "MonsterAllLetters": null, "Stones": {"string": ["k", "b"]}}, {"@SegmentTime": "11", "@spawnIds": "25,28,60", "MonsterRequiredLetters": {"string": "k"}, "MonsterAllLetters": null, "Stones": {"string": ["t", "k", {"@bonusScore": "100", "#text": "BonusLetter"}]}}]}}}