{"XMLLevel": {"@CollectableMonster": "", "@HideCallout": "3", "@LettersGroup": "4", "@SegmentTime": "10", "@StoneType": "1", "@monsterInputType": "Letter", "Segments": {"Segment": [{"@SegmentTime": "10", "@spawnIds": "", "MonsterRequiredLetters": {"string": "ty"}, "MonsterAllLetters": null, "Stones": {"string": [{"@spawnId": "18", "#text": "dz"}, {"@spawnId": "19", "#text": "dz"}, {"@spawnId": "36", "#text": "dz"}, {"@spawnId": "45", "#text": "ty"}, {"@spawnId": "57", "#text": "dz"}, {"@spawnId": "56", "#text": "ty"}, {"@spawnId": "8", "#text": "Shield"}, {"@bonusScore": "275", "@spawnId": "9", "#text": "BonusLetter"}]}}, {"@SegmentTime": "10", "@spawnIds": "87,78,64,60,36,79,86,63,45", "MonsterRequiredLetters": {"string": "dz"}, "MonsterAllLetters": null, "Stones": {"string": ["o", "d", "n", "n", "ty", "ty", "r", "f", "dz"]}}, {"@SegmentTime": "10", "@spawnIds": "", "MonsterRequiredLetters": {"string": "r"}, "MonsterAllLetters": null, "Stones": {"string": [{"@spawnId": "21", "#text": "dz"}, {"@spawnId": "5", "#text": "n"}, {"@spawnId": "22", "#text": "ty"}, {"@spawnId": "92", "#text": "ty"}, {"@spawnId": "58", "#text": "n"}, {"@spawnId": "91", "#text": "o"}, {"@spawnId": "62", "#text": "ty"}, {"@spawnId": "4", "#text": "r"}]}}, {"@SegmentTime": "10", "@spawnIds": "87,78,64,60,36,79,86,63,45", "MonsterRequiredLetters": {"string": "f"}, "MonsterAllLetters": null, "Stones": {"string": ["n", "d", "f", "dz", "d", "r", "f", "o", "f"]}}, {"@SegmentTime": "10", "@spawnIds": "", "MonsterRequiredLetters": {"string": "f"}, "MonsterAllLetters": null, "Stones": {"string": [{"@spawnId": "18", "#text": "f"}, {"@spawnId": "19", "#text": "f"}, {"@spawnId": "36", "#text": "dz"}, {"@spawnId": "45", "#text": "dz"}, {"@spawnId": "57", "#text": "ty"}, {"@spawnId": "56", "#text": "f"}, {"@spawnId": "8", "#text": "Shield"}, {"@bonusScore": "275", "@spawnId": "9", "#text": "BonusLetter"}]}}]}}}