{"XMLLevel": {"@CollectableMonster": "", "@HideCallout": "2", "@LettersGroup": "4", "@SegmentTime": "10", "@StoneType": "1", "@monsterInputType": "LetterInWord", "Segments": {"Segment": [{"@SegmentTime": "10", "@spawnIds": "5,4,74,75,56,57,87,86,60", "MonsterRequiredLetters": {"string": "t"}, "MonsterAllLetters": {"string": ["X", "h", "o", "l", "a"]}, "Stones": {"string": ["e", "t", {"@spawnId": "24", "#text": "o"}, {"@spawnId": "22", "#text": "o"}, {"@spawnId": "30", "#text": "r"}, {"@spawnId": "20", "#text": "r"}, {"@spawnId": "20", "#text": "v"}, {"@spawnId": "22", "#text": "t"}]}}, {"@SegmentTime": "10", "@spawnIds": "5,4,74,75,56,57,87,86,60", "MonsterRequiredLetters": {"string": "r"}, "MonsterAllLetters": {"string": ["X", "o", "n", "a"]}, "Stones": {"string": ["e", "o", "w", "v", {"@spawnId": "22", "#text": "r"}, {"@spawnId": "20", "#text": "v"}, {"@spawnId": "28", "#text": "r"}, {"@spawnId": "22", "#text": "r"}]}}, {"@SegmentTime": "10", "@spawnIds": "5,4,74,75,56,57,87,86,60", "MonsterRequiredLetters": {"string": "r"}, "MonsterAllLetters": {"string": ["X", "o", "n", "a"]}, "Stones": {"string": ["r", {"@spawnId": "30", "#text": "e"}, {"@spawnId": "28", "#text": "o"}, {"@spawnId": "28", "#text": "o"}, {"@spawnId": "22", "#text": "v"}, {"@spawnId": "26", "#text": "t"}, {"@spawnId": "26", "#text": "r"}]}}, {"@SegmentTime": "10", "@spawnIds": "5,4,74,75,56,57,87,86,60", "MonsterRequiredLetters": {"string": "w"}, "MonsterAllLetters": {"string": ["X", "o", "n", "a"]}, "Stones": {"string": ["o", {"@spawnId": "24", "#text": "w"}, {"@spawnId": "24", "#text": "o"}, {"@spawnId": "28", "#text": "w"}, {"@spawnId": "26", "#text": "o"}, {"@spawnId": "30", "#text": "w"}]}}, {"@SegmentTime": "10", "@spawnIds": "5,4,74,75,56,57,87,86,60", "MonsterRequiredLetters": {"string": "t"}, "MonsterAllLetters": {"string": ["X", "h", "o", "l", "a"]}, "Stones": {"string": ["e", "w", "t", "k", {"@spawnId": "28", "#text": "r"}, {"@spawnId": "26", "#text": "r"}, {"@spawnId": "28", "#text": "t"}]}}]}}}