{"XMLLevel": {"@CollectableMonster": "Hypnosis", "@HideCallout": "-1", "@LettersGroup": "4", "@SegmentTime": "11", "@StoneType": "1", "@monsterInputType": "Letter", "Segments": {"Segment": [{"@SegmentTime": "11", "@spawnIds": "67,45,79", "MonsterRequiredLetters": {"string": "\u0a8a"}, "MonsterAllLetters": null, "Stones": {"string": ["\u0a85\u0a83", "\u0a8a", "\u0a90"]}}, {"@SegmentTime": "11", "@spawnIds": "66,36,78", "MonsterRequiredLetters": {"string": "\u0a87"}, "MonsterAllLetters": null, "Stones": {"string": ["\u0a87", "\u0a87", "\u0a89"]}}, {"@SegmentTime": "11", "@spawnIds": "18,21,26", "MonsterRequiredLetters": {"string": "\u0a86"}, "MonsterAllLetters": null, "Stones": {"string": ["\u0a86", "\u0a8a", "\u0a88"]}}, {"@SegmentTime": "11", "@spawnIds": "19,22,27", "MonsterRequiredLetters": {"string": "\u0a85"}, "MonsterAllLetters": null, "Stones": {"string": ["\u0a85", "\u0a85\u0a82", "\u0a93"]}}, {"@SegmentTime": "11", "@spawnIds": "87,27,26,86", "MonsterRequiredLetters": {"string": "\u0a89"}, "MonsterAllLetters": null, "Stones": {"string": ["\u0a89", "\u0a89", "\u0a87", {"@bonusScore": "125", "#text": "BonusLetter"}]}}]}}}