{"XMLLevel": {"@CollectableMonster": "", "@HideCallout": "3", "@LettersGroup": "4", "@SegmentTime": "9", "@StoneType": "1", "@monsterInputType": "SoundLetter", "Segments": {"Segment": [{"@SegmentTime": "10", "@spawnIds": "", "MonsterRequiredLetters": {"string": "d"}, "MonsterAllLetters": null, "Stones": {"string": [{"@spawnId": "1", "#text": "t th"}, {"@spawnId": "21", "#text": "t th"}, {"@spawnId": "76", "#text": "g"}, {"@spawnId": "73", "#text": "c"}, {"@spawnId": "22", "#text": "m"}, {"@spawnId": "0", "#text": "d"}]}}, {"@SegmentTime": "10", "@spawnIds": "0,1,21,22,73,76", "MonsterRequiredLetters": {"string": "r"}, "MonsterAllLetters": null, "Stones": {"string": ["n", "s", "c", "s", "k l", "r"]}}, {"@SegmentTime": "10", "@spawnIds": "", "MonsterRequiredLetters": {"string": "s"}, "MonsterAllLetters": null, "Stones": {"string": [{"@spawnId": "59", "#text": "y"}, {"@spawnId": "22", "#text": "r"}, {"@spawnId": "61", "#text": "t th"}, {"@spawnId": "18", "#text": "u"}, {"@spawnId": "21", "#text": "w"}, {"@spawnId": "19", "#text": "s"}]}}, {"@SegmentTime": "10", "@spawnIds": "18,19,21,22,59,61", "MonsterRequiredLetters": {"string": "n"}, "MonsterAllLetters": null, "Stones": {"string": ["b", "k l", "dh", "d", "n", "n"]}}, {"@SegmentTime": "10", "@spawnIds": "", "MonsterRequiredLetters": {"string": "g"}, "MonsterAllLetters": null, "Stones": {"string": [{"@spawnId": "4", "#text": "y"}, {"@spawnId": "57", "#text": "dh"}, {"@spawnId": "91", "#text": "b"}, {"@spawnId": "5", "#text": "w"}, {"@spawnId": "56", "#text": "u"}, {"@spawnId": "92", "#text": "g"}]}}]}}}