{"XMLLevel": {"@CollectableMonster": "", "@HideCallout": "1", "@LettersGroup": "6", "@SegmentTime": "12", "@StoneType": "2", "@monsterInputType": "Word", "Segments": {"Segment": [{"@SegmentTime": "12", "@spawnIds": "", "MonsterRequiredLetters": {"string": ["a", "z", "a"]}, "MonsterAllLetters": null, "Stones": {"string": [{"@spawnId": "36", "#text": "d"}, {"@spawnId": "65", "#text": "n"}, {"@spawnId": "68", "#text": "n"}, {"@spawnId": "45", "#text": "b"}, {"@spawnId": "94", "#text": "a"}, {"@spawnId": "28", "#text": "z"}, {"@spawnId": "25", "#text": "a"}, {"@bonusScore": "275", "@spawnId": "93", "#text": "BonusLetter"}]}}, {"@SegmentTime": "12", "@spawnIds": "", "MonsterRequiredLetters": {"string": ["l", "a", "v", "a"]}, "MonsterAllLetters": null, "Stones": {"string": [{"@spawnId": "59", "#text": "n"}, {"@spawnId": "45", "#text": "h"}, {"@spawnId": "2", "#text": "z"}, {"@spawnId": "36", "#text": "l"}, {"@spawnId": "79", "#text": "a"}, {"@spawnId": "78", "#text": "v"}, {"@spawnId": "61", "#text": "a"}, {"@bonusScore": "275", "@spawnId": "3", "#text": "BonusLetter"}]}}, {"@SegmentTime": "12", "@spawnIds": "", "MonsterRequiredLetters": {"string": ["g", "a", "n", "a"]}, "MonsterAllLetters": null, "Stones": {"string": [{"@spawnId": "45", "#text": "b"}, {"@spawnId": "68", "#text": "l"}, {"@spawnId": "65", "#text": "l"}, {"@spawnId": "36", "#text": "l"}, {"@spawnId": "93", "#text": "g"}, {"@spawnId": "25", "#text": "a"}, {"@spawnId": "28", "#text": "n"}, {"@spawnId": "94", "#text": "a"}]}}, {"@SegmentTime": "12", "@spawnIds": "", "MonsterRequiredLetters": {"string": ["h", "a", "b", "a"]}, "MonsterAllLetters": null, "Stones": {"string": [{"@spawnId": "61", "#text": "l"}, {"@spawnId": "36", "#text": "v"}, {"@spawnId": "3", "#text": "f"}, {"@spawnId": "45", "#text": "h"}, {"@spawnId": "78", "#text": "a"}, {"@spawnId": "79", "#text": "b"}, {"@spawnId": "59", "#text": "a"}, {"@bonusScore": "275", "@spawnId": "2", "#text": "BonusLetter"}]}}, {"@SegmentTime": "12", "@spawnIds": "", "MonsterRequiredLetters": {"string": ["a", "z", "a"]}, "MonsterAllLetters": null, "Stones": {"string": [{"@spawnId": "11", "#text": "m"}, {"@spawnId": "75", "#text": "h"}, {"@spawnId": "20", "#text": "m"}, {"@spawnId": "59", "#text": "g"}, {"@spawnId": "74", "#text": "a"}, {"@spawnId": "12", "#text": "z"}, {"@spawnId": "23", "#text": "a"}, {"@bonusScore": "275", "@spawnId": "61", "#text": "BonusLetter"}]}}]}}}