{"XMLLevel": {"@CollectableMonster": "", "@HideCallout": "2", "@LettersGroup": "4", "@SegmentTime": "10", "@StoneType": "1", "@monsterInputType": "LetterInWord", "Segments": {"Segment": [{"@SegmentTime": "10", "@spawnIds": "5,4,74,75,56,57,87,86,60", "MonsterRequiredLetters": {"string": "k"}, "MonsterAllLetters": {"string": ["X", "o", "l", "o"]}, "Stones": {"string": ["g", "l", "g", "k", "n", "n", "h", "h", "k"]}}, {"@SegmentTime": "10", "@spawnIds": "5,4,74,75,56,57,87,86,60", "MonsterRequiredLetters": {"string": "s"}, "MonsterAllLetters": {"string": ["X", "o", "l", "o"]}, "Stones": {"string": ["l", "f", "h", "g", "l", "g", "o", "o", "s"]}}, {"@SegmentTime": "10", "@spawnIds": "5,4,74,75,56,57,87,86,60", "MonsterRequiredLetters": {"string": "z"}, "MonsterAllLetters": {"string": ["X", "o", "t", "o"]}, "Stones": {"string": ["g", "o", "v", "f", "r", "n", "s", "f", "z"]}}, {"@SegmentTime": "10", "@spawnIds": "5,4,74,75,56,57,87,86,60", "MonsterRequiredLetters": {"string": "g"}, "MonsterAllLetters": {"string": ["X", "o", "g", "o"]}, "Stones": {"string": ["f", "g", "l", "t", "r", "z", "l", "o", "g"]}}, {"@SegmentTime": "10", "@spawnIds": "5,4,74,75,56,57,87,86,60", "MonsterRequiredLetters": {"string": "z"}, "MonsterAllLetters": {"string": ["X", "o", "t", "o"]}, "Stones": {"string": ["k", "h", "l", "r", "o", "t", "f", "t", "z"]}}]}}}