{"XMLLevel": {"@CollectableMonster": "", "@HideCallout": "-1", "@LettersGroup": "1", "@SegmentTime": "13", "@StoneType": "1", "@monsterInputType": "SoundWord", "Segments": {"Segment": [{"@SegmentTime": "13", "@spawnIds": "", "MonsterRequiredLetters": {"string": ["p", "a", "t"]}, "MonsterAllLetters": null, "Stones": {"string": [{"@spawnId": "6", "#text": "p"}, {"@spawnId": "93", "#text": "a"}, {"@spawnId": "25", "#text": "t"}]}}, {"@SegmentTime": "13", "@spawnIds": "", "MonsterRequiredLetters": {"string": ["m", "a", "p"]}, "MonsterAllLetters": null, "Stones": {"string": [{"@spawnId": "7", "#text": "m"}, {"@spawnId": "94", "#text": "a"}, {"@spawnId": "28", "#text": "p"}]}}, {"@SegmentTime": "13", "@spawnIds": "", "MonsterRequiredLetters": {"string": ["t", "a", "m"]}, "MonsterAllLetters": null, "Stones": {"string": [{"@spawnId": "25", "#text": "t"}, {"@spawnId": "93", "#text": "a"}, {"@spawnId": "6", "#text": "m"}]}}, {"@SegmentTime": "13", "@spawnIds": "", "MonsterRequiredLetters": {"string": ["m", "a", "t"]}, "MonsterAllLetters": null, "Stones": {"string": [{"@spawnId": "28", "#text": "m"}, {"@spawnId": "94", "#text": "a"}, {"@spawnId": "7", "#text": "t"}]}}, {"@SegmentTime": "13", "@spawnIds": "", "MonsterRequiredLetters": {"string": ["c", "a", "p"]}, "MonsterAllLetters": null, "Stones": {"string": [{"@spawnId": "94", "#text": "c"}, {"@spawnId": "59", "#text": "a"}, {"@spawnId": "93", "#text": "p"}, {"@bonusScore": "175", "@spawnId": "61", "#text": "BonusLetter"}]}}]}}}