<XMLLevel CollectableMonster="" HideCallout="-1" LettersGroup="3" SegmentTime="11" StoneType="1" monsterInputType="Letter">
  <Segments>
    <Segment SegmentTime="11" spawnIds="19,22,27">
      
	  <MonsterRequiredLetters>
		<string>466</string>
	  </MonsterRequiredLetters>
	  <MonsterAllLetters>
	  </MonsterAllLetters>
	  <Stones>
        <string>406</string>
        <string>466</string>
        <string>84</string>
      </Stones>
    </Segment>
	<Segment SegmentTime="11" spawnIds="">
      
	  <MonsterRequiredLetters>
		<string>17</string>
	  </MonsterRequiredLetters>
	  <MonsterAllLetters>
	  </MonsterAllLetters>
	  <Stones>
        <string spawnId="18">466</string>
        <string spawnId="21">418</string>
        <string spawnId="26">17</string>
      </Stones>
    </Segment>
	<Segment SegmentTime="11" spawnIds="89,54,95">
      
	  <MonsterRequiredLetters>
		<string>406</string>
	  </MonsterRequiredLetters>
	  <MonsterAllLetters>
	  </MonsterAllLetters>
	  <Stones>
        <string>406</string>
        <string>384</string>
        <string>418</string>
      </Stones>
    </Segment>
	<Segment SegmentTime="11" spawnIds="">
      
	  <MonsterRequiredLetters>
		<string>360</string>
	  </MonsterRequiredLetters>
	  <MonsterAllLetters>
	  </MonsterAllLetters>
	  <Stones>
        <string spawnId="90">418</string>
        <string spawnId="55">360</string>
        <string spawnId="96">17</string>
      </Stones>
    </Segment>
	<Segment SegmentTime="11" spawnIds="61,59,93,94">
      
	  <MonsterRequiredLetters>
		<string>430</string>
	  </MonsterRequiredLetters>
	  <MonsterAllLetters>
	  </MonsterAllLetters>
	  <Stones>
        <string>430</string>
        <string>36</string>
        <string>454</string>
		<string bonusScore="150">BonusLetter</string>
      </Stones>
    </Segment>
  </Segments>
</XMLLevel>