<XMLLevel CollectableMonster="Ice" HideCallout="-1" LettersGroup="6" SegmentTime="11" StoneType="1" monsterInputType="Letter">
  <Segments>
    <Segment SegmentTime="11" spawnIds="">
    	
    	<MonsterRequiredLetters>
    		<string>177</string>
    	</MonsterRequiredLetters>
    	<MonsterAllLetters>
    	</MonsterAllLetters>
    	<Stones>
    		<string spawnId="84">155</string>
    		<string spawnId="54">146</string>
    		<string spawnId="55">177</string>
			<string spawnId="81">177</string>
    	</Stones>
	</Segment>
	<Segment SegmentTime="11" spawnIds="">
		
		<MonsterRequiredLetters>
			<string>192</string>
		</MonsterRequiredLetters>
	  	<MonsterAllLetters>
	  	</MonsterAllLetters>
	  	<Stones>
        	<string spawnId="82">216</string>
        	<string spawnId="8">192</string>
        	<string spawnId="83">30</string>
			<string spawnId="9">29</string>
      	</Stones>
    </Segment>
    <Segment SegmentTime="11" spawnIds="">
		
      	<MonsterRequiredLetters>
			<string>216</string>
	  	</MonsterRequiredLetters>
	  	<MonsterAllLetters>
	  	</MonsterAllLetters>
	  	<Stones>
	        <string spawnId="3">180</string>
	        <string spawnId="70">30</string>
	        <string spawnId="71">191</string>
			<string spawnId="2">216</string>
      	</Stones>
    </Segment>
	<Segment SegmentTime="11" spawnIds="">
		
      	<MonsterRequiredLetters>
			<string>180</string>
	  	</MonsterRequiredLetters>
	  	<MonsterAllLetters>
	  	</MonsterAllLetters>
	  	<Stones>
			<string spawnId="23">201</string>
	        <string spawnId="74">167</string>
	        <string spawnId="75">180</string>
			<string spawnId="20">143</string>
      	</Stones>
	</Segment>

	<Segment SegmentTime="11" spawnIds="">
		
      	<MonsterRequiredLetters>
			<string>189</string>
	  	</MonsterRequiredLetters>
	  	<MonsterAllLetters>
	  	</MonsterAllLetters>
	  	<Stones>
	        <string spawnId="89">168</string>
	        <string spawnId="96">29</string>
	        <string spawnId="95">203</string>
			<string spawnId="90">189</string>
	        <string bonusScore="125" spawnId="18">BonusLetter</string>
			<string bonusScore="125" spawnId="19">BonusLetter</string>
      	</Stones>
	</Segment>
  </Segments>
</XMLLevel>