{"XMLLevel": {"@CollectableMonster": "", "@HideCallout": "1", "@LettersGroup": "5", "@SegmentTime": "11", "@StoneType": "1", "@monsterInputType": "SoundWord", "Segments": {"Segment": [{"@SegmentTime": "11", "@spawnIds": "", "MonsterRequiredLetters": {"string": ["l", "\u00f3", "c"]}, "MonsterAllLetters": null, "Stones": {"string": [{"@spawnId": "72", "#text": "g"}, {"@spawnId": "81", "#text": "th"}, {"@spawnId": "8", "#text": "u"}, {"@spawnId": "9", "#text": "l"}, {"@spawnId": "69", "#text": "\u00f3"}, {"@spawnId": "84", "#text": "c"}]}}, {"@SegmentTime": "11", "@spawnIds": "72,81,8,9,69,84", "MonsterRequiredLetters": {"string": ["kh", "u", "n", "g"]}, "MonsterAllLetters": null, "Stones": {"string": ["th", "kh", "u", "n", "g"]}}, {"@SegmentTime": "11", "@spawnIds": "72,81,8,9,69,84", "MonsterRequiredLetters": {"string": ["h", "\u00f2", "n"]}, "MonsterAllLetters": null, "Stones": {"string": ["c", "r", "r", "h", "\u00f2", "n"]}}, {"@SegmentTime": "11", "@spawnIds": "72,81,8,9,69,84", "MonsterRequiredLetters": {"string": ["n", "u", "ng"]}, "MonsterAllLetters": null, "Stones": {"string": ["kh", "c", "n", "u", "ng"]}}, {"@SegmentTime": "11", "@spawnIds": "72,81,8,9,69,84", "MonsterRequiredLetters": {"string": ["l", "o", "n"]}, "MonsterAllLetters": null, "Stones": {"string": ["r", "g", "u", "l", "o", "n"]}}]}}}