{"XMLLevel": {"@CollectableMonster": "", "@HideCallout": "4", "@LettersGroup": "14", "@SegmentTime": "11", "@StoneType": "1", "@monsterInputType": "Letter", "Segments": {"Segment": [{"@SegmentTime": "10", "@spawnIds": "", "MonsterRequiredLetters": {"string": "\u063a"}, "MonsterAllLetters": null, "Stones": {"string": [{"@spawnId": "10", "#text": "\u0642"}, {"@spawnId": "61", "#text": "\u0642"}, {"@spawnId": "71", "#text": "\u0627"}, {"@spawnId": "96", "#text": "\u063a"}, {"@spawnId": "13", "#text": "\u063a"}, {"@spawnId": "95", "#text": "\u062d"}, {"@spawnId": "55", "#text": "\u0627"}, {"@spawnId": "70", "#text": "\u0642"}]}}, {"@SegmentTime": "10", "@spawnIds": "", "MonsterRequiredLetters": {"string": "\u062d"}, "MonsterAllLetters": null, "Stones": {"string": [{"@spawnId": "87", "#text": "\u0631"}, {"@spawnId": "78", "#text": "\u0631"}, {"@spawnId": "64", "#text": "\u063a"}, {"@spawnId": "60", "#text": "\u062f"}, {"@spawnId": "36", "#text": "\u062d"}, {"@spawnId": "79", "#text": "\u062d"}, {"@spawnId": "86", "#text": "\u062f"}, {"@spawnId": "45", "#text": "\u062d"}]}}, {"@SegmentTime": "10", "@spawnIds": "", "MonsterRequiredLetters": {"string": "\u0627"}, "MonsterAllLetters": null, "Stones": {"string": [{"@spawnId": "20", "#text": "\u0627"}, {"@spawnId": "23", "#text": "\u06d5"}, {"@spawnId": "54", "#text": "\u0627"}, {"@spawnId": "55", "#text": "\u062f"}, {"@spawnId": "58", "#text": "\u0627"}, {"@spawnId": "21", "#text": "Shield"}, {"@bonusScore": "275", "@spawnId": "22", "#text": "BonusLetter"}]}}, {"@SegmentTime": "10", "@spawnIds": "", "MonsterRequiredLetters": {"string": "\u063a"}, "MonsterAllLetters": null, "Stones": {"string": [{"@spawnId": "18", "#text": "\u06d5"}, {"@spawnId": "19", "#text": "\u063a"}, {"@spawnId": "36", "#text": "\u06d5"}, {"@spawnId": "45", "#text": "\u062d"}, {"@spawnId": "57", "#text": "\u063a"}, {"@spawnId": "56", "#text": "\u0627"}, {"@spawnId": "8", "#text": "Shield"}, {"@bonusScore": "275", "@spawnId": "9", "#text": "BonusLetter"}]}}, {"@SegmentTime": "10", "@spawnIds": "87,78,64,60,36,79,86,63,45", "MonsterRequiredLetters": {"string": "\u06d5"}, "MonsterAllLetters": null, "Stones": {"string": ["\u063a", "\u063a", "\u06d5", "\u0627", "\u06d5", "\u062f", "\u0642", "\u06d5", "\u063a"]}}]}}}