{"XMLLevel": {"@CollectableMonster": "", "@HideCallout": "1", "@LettersGroup": "5", "@SegmentTime": "9", "@StoneType": "1", "@monsterInputType": "Letter", "Segments": {"Segment": [{"@SegmentTime": "9", "@spawnIds": "", "MonsterRequiredLetters": {"string": "p"}, "MonsterAllLetters": null, "Stones": {"string": [{"@spawnId": "60", "#text": "p"}, {"@spawnId": "54", "#text": "n"}, {"@spawnId": "72", "#text": "n"}, {"@spawnId": "82", "#text": "ch"}, {"@spawnId": "69", "#text": "n"}, {"@spawnId": "3", "#text": "l"}, {"@spawnId": "83", "#text": "ch"}, {"@spawnId": "55", "#text": "n"}, {"@spawnId": "2", "#text": "p"}]}}, {"@SegmentTime": "9", "@spawnIds": "", "MonsterRequiredLetters": {"string": "u"}, "MonsterAllLetters": null, "Stones": {"string": [{"@spawnId": "81", "#text": "ch"}, {"@spawnId": "12", "#text": "p"}, {"@spawnId": "70", "#text": "u"}, {"@spawnId": "55", "#text": "p"}, {"@spawnId": "11", "#text": "ch"}, {"@spawnId": "71", "#text": "n"}, {"@spawnId": "84", "#text": "n"}, {"@spawnId": "61", "#text": "ch"}, {"@spawnId": "59", "#text": "u"}, {"@bonusScore": "275", "@spawnId": "54", "#text": "BonusLetter"}]}}, {"@SegmentTime": "9", "@spawnIds": "60,54,72,82,69,3,83,55,2", "MonsterRequiredLetters": {"string": "l"}, "MonsterAllLetters": null, "Stones": {"string": ["l", "l", "ch", "u", "l", "u", "p", "n", "l"]}}, {"@SegmentTime": "9", "@spawnIds": "", "MonsterRequiredLetters": {"string": "n"}, "MonsterAllLetters": null, "Stones": {"string": [{"@spawnId": "84", "#text": "u"}, {"@spawnId": "11", "#text": "ch"}, {"@spawnId": "71", "#text": "ch"}, {"@spawnId": "54", "#text": "ch"}, {"@spawnId": "12", "#text": "p"}, {"@spawnId": "70", "#text": "u"}, {"@spawnId": "81", "#text": "l"}, {"@spawnId": "59", "#text": "u"}, {"@spawnId": "61", "#text": "n"}, {"@bonusScore": "275", "@spawnId": "55", "#text": "BonusLetter"}]}}, {"@SegmentTime": "9", "@spawnIds": "60,54,72,82,69,3,83,55,2", "MonsterRequiredLetters": {"string": "p"}, "MonsterAllLetters": null, "Stones": {"string": ["ch", "ch", "p", "p", "ch", "u", "n", "u", "p"]}}]}}}