{"XMLLevel": {"@CollectableMonster": "", "@HideCallout": "-1", "@LettersGroup": "1", "@SegmentTime": "11", "@StoneType": "1", "@monsterInputType": "LetterInWord", "Segments": {"Segment": [{"@SegmentTime": "11", "@spawnIds": "19,22,27", "MonsterRequiredLetters": {"string": "a"}, "MonsterAllLetters": {"string": ["X", "h", "m", "a", "k"]}, "Stones": {"string": ["h", "b", "a"]}}, {"@SegmentTime": "11", "@spawnIds": "", "MonsterRequiredLetters": {"string": "h"}, "MonsterAllLetters": {"string": ["X", "a", "l", "\u0131"]}, "Stones": {"string": [{"@spawnId": "18", "#text": "p"}, {"@spawnId": "21", "#text": "p"}, {"@spawnId": "26", "#text": "h"}]}}, {"@SegmentTime": "11", "@spawnIds": "89,54,95", "MonsterRequiredLetters": {"string": "h"}, "MonsterAllLetters": {"string": ["X", "a", "l", "\u0131"]}, "Stones": {"string": ["m", "m", "h"]}}, {"@SegmentTime": "11", "@spawnIds": "", "MonsterRequiredLetters": {"string": "h"}, "MonsterAllLetters": {"string": ["X", "a", "l", "\u0131"]}, "Stones": {"string": [{"@spawnId": "90", "#text": "m"}, {"@spawnId": "55", "#text": "b"}, {"@spawnId": "96", "#text": "h"}]}}, {"@SegmentTime": "11", "@spawnIds": "61,59,93,94", "MonsterRequiredLetters": {"string": "m"}, "MonsterAllLetters": {"string": ["X", "a", "m", "a"]}, "Stones": {"string": ["a", "p", "m", {"@bonusScore": "150", "#text": "BonusLetter"}]}}]}}}