{"XMLLevel": {"@CollectableMonster": "", "@HideCallout": "3", "@LettersGroup": "4", "@SegmentTime": "9", "@StoneType": "1", "@monsterInputType": "SoundLetter", "Segments": {"Segment": [{"@SegmentTime": "10", "@spawnIds": "", "MonsterRequiredLetters": {"string": "o"}, "MonsterAllLetters": null, "Stones": {"string": [{"@spawnId": "1", "#text": "g"}, {"@spawnId": "21", "#text": "d"}, {"@spawnId": "76", "#text": "l"}, {"@spawnId": "73", "#text": "l"}, {"@spawnId": "22", "#text": "w"}, {"@spawnId": "0", "#text": "o"}]}}, {"@SegmentTime": "10", "@spawnIds": "0,1,21,22,73,76", "MonsterRequiredLetters": {"string": "w"}, "MonsterAllLetters": null, "Stones": {"string": ["o", "g", "w", "o", "o", "w"]}}, {"@SegmentTime": "10", "@spawnIds": "", "MonsterRequiredLetters": {"string": "g"}, "MonsterAllLetters": null, "Stones": {"string": [{"@spawnId": "59", "#text": "o"}, {"@spawnId": "22", "#text": "l"}, {"@spawnId": "61", "#text": "l"}, {"@spawnId": "18", "#text": "w"}, {"@spawnId": "21", "#text": "g"}, {"@spawnId": "19", "#text": "g"}]}}, {"@SegmentTime": "10", "@spawnIds": "18,19,21,22,59,61", "MonsterRequiredLetters": {"string": "d"}, "MonsterAllLetters": null, "Stones": {"string": ["l", "x", "l", "g", "d", "d"]}}, {"@SegmentTime": "10", "@spawnIds": "", "MonsterRequiredLetters": {"string": "l"}, "MonsterAllLetters": null, "Stones": {"string": [{"@spawnId": "4", "#text": "d"}, {"@spawnId": "57", "#text": "q"}, {"@spawnId": "91", "#text": "l"}, {"@spawnId": "5", "#text": "o"}, {"@spawnId": "56", "#text": "g"}, {"@spawnId": "92", "#text": "l"}]}}]}}}