{"XMLLevel": {"@CollectableMonster": "", "@HideCallout": "-1", "@LettersGroup": "2", "@SegmentTime": "13", "@StoneType": "1", "@monsterInputType": "SoundWord", "Segments": {"Segment": [{"@SegmentTime": "13", "@spawnIds": "21,60,22", "MonsterRequiredLetters": {"string": ["l", "e", "r", "u"]}, "MonsterAllLetters": null, "Stones": {"string": ["l", "e", "r", {"@spawnId": "30", "#text": "u"}]}}, {"@SegmentTime": "13", "@spawnIds": "90,55,96", "MonsterRequiredLetters": null, "MonsterAllLetters": null, "Stones": {"string": ["h", "l", "b"]}}, {"@SegmentTime": "13", "@spawnIds": "89,54,95", "MonsterRequiredLetters": {"string": ["l", "e", "f", "a"]}, "MonsterAllLetters": null, "Stones": {"string": ["l", "e", "f", {"@spawnId": "28", "#text": "a"}]}}, {"@SegmentTime": "13", "@spawnIds": "59,93,36", "MonsterRequiredLetters": {"string": ["s", "e", "s", "a"]}, "MonsterAllLetters": null, "Stones": {"string": ["s", "e", "s", {"@spawnId": "22", "#text": "a"}]}}, {"@SegmentTime": "13", "@spawnIds": "61,94,45", "MonsterRequiredLetters": {"string": ["q", "e", "t", "a"]}, "MonsterAllLetters": null, "Stones": {"string": ["q", "e", "t", {"@spawnId": "28", "#text": "a"}]}}]}}}