<XMLLevel CollectableMonster="" HideCallout="-1" LettersGroup="12" SegmentTime="11" StoneType="1" monsterInputType="Word">
  <Segments>

<Segment SegmentTime="11" spawnIds="20,75,15,23,74,14,11,12,60">
      
	  <MonsterRequiredLetters>
		<string>s</string><string>ↄ</string></MonsterRequiredLetters>
	  <MonsterAllLetters>
	  </MonsterAllLetters>
	  <Stones>
        <string>ↄ</string><string>m</string><string>s</string><string>ny</string></Stones>
    </Segment>


      <Segment SegmentTime="11" spawnIds="20,75,15,23,74,14,11,12,60">
      
	  <MonsterRequiredLetters>
		<string>p</string><string>ↄ</string></MonsterRequiredLetters>
	  <MonsterAllLetters>
	  </MonsterAllLetters>
	  <Stones>
        <string>ↄ</string><string>n</string><string>p</string><string>gy</string></Stones>
    </Segment>


	<Segment SegmentTime="11" spawnIds="20,75,15,23,74,14,11,12,60">
      
	  <MonsterRequiredLetters>
		<string>k</string><string>ↄ</string></MonsterRequiredLetters>
	  <MonsterAllLetters>
	  </MonsterAllLetters>
	  <Stones>
        <string>ↄ</string><string>y</string><string>k</string><string>n</string></Stones>
    </Segment>


<Segment SegmentTime="11" spawnIds="20,75,15,23,74,14,11,12,60">
      
	  <MonsterRequiredLetters>
		<string>t</string><string>ↄ</string></MonsterRequiredLetters>
	  <MonsterAllLetters>
	  </MonsterAllLetters>
	  <Stones>
        <string>ↄ</string><string>i</string><string>t</string><string>a</string></Stones>
    </Segment>

    <Segment SegmentTime="11" spawnIds="20,75,15,23,74,14,11,12,60">
      
	  <MonsterRequiredLetters>
		<string>d</string><string>ↄ</string></MonsterRequiredLetters>
	  <MonsterAllLetters>
	  </MonsterAllLetters>
	  <Stones>
        <string>ↄ</string><string>a</string><string>d</string><string>y</string></Stones>
    </Segment>


  </Segments>
</XMLLevel>