{"XMLLevel": {"@CollectableMonster": "", "@HideCallout": "4", "@LettersGroup": "3", "@SegmentTime": "10", "@StoneType": "2", "@monsterInputType": "LetterInWord", "Segments": {"Segment": [{"@SegmentTime": "10", "@spawnIds": "", "MonsterRequiredLetters": {"string": "n"}, "MonsterAllLetters": {"string": ["X", "a", "k", "u"]}, "Stones": {"string": [{"@spawnId": "14", "#text": "a"}, {"@spawnId": "74", "#text": "r"}, {"@spawnId": "20", "#text": "n"}]}}, {"@SegmentTime": "10", "@spawnIds": "", "MonsterRequiredLetters": {"string": "t"}, "MonsterAllLetters": {"string": ["X", "a", "k", "u"]}, "Stones": {"string": [{"@spawnId": "15", "#text": "k"}, {"@spawnId": "75", "#text": "n"}, {"@spawnId": "23", "#text": "t"}]}}, {"@SegmentTime": "10", "@spawnIds": "", "MonsterRequiredLetters": {"string": "k"}, "MonsterAllLetters": {"string": ["X", "e", "k", "e"]}, "Stones": {"string": [{"@spawnId": "28", "#text": "l"}, {"@spawnId": "94", "#text": "d"}, {"@spawnId": "45", "#text": "k"}]}}, {"@SegmentTime": "10", "@spawnIds": "", "MonsterRequiredLetters": {"string": "t"}, "MonsterAllLetters": {"string": ["X", "a", "k", "u"]}, "Stones": {"string": [{"@spawnId": "25", "#text": "n"}, {"@spawnId": "93", "#text": "d"}, {"@spawnId": "36", "#text": "t"}]}}, {"@SegmentTime": "10", "@spawnIds": "", "MonsterRequiredLetters": {"string": "r"}, "MonsterAllLetters": {"string": ["X", "a", "r", "a"]}, "Stones": {"string": [{"@spawnId": "78", "#text": "t"}, {"@spawnId": "60", "#text": "a"}, {"@spawnId": "79", "#text": "r"}]}}]}}}