{"XMLLevel": {"@CollectableMonster": "", "@HideCallout": "1", "@LettersGroup": "5", "@SegmentTime": "9", "@StoneType": "1", "@monsterInputType": "SoundLetter", "Segments": {"Segment": [{"@SegmentTime": "9", "@spawnIds": "", "MonsterRequiredLetters": {"string": "n"}, "MonsterAllLetters": null, "Stones": {"string": [{"@spawnId": "67", "#text": "b"}, {"@spawnId": "74", "#text": "b"}, {"@spawnId": "82", "#text": "u"}, {"@spawnId": "71", "#text": "x"}, {"@spawnId": "70", "#text": "u"}, {"@spawnId": "83", "#text": "t"}, {"@spawnId": "75", "#text": "x"}, {"@spawnId": "66", "#text": "t"}, {"@spawnId": "60", "#text": "n"}]}}, {"@SegmentTime": "9", "@spawnIds": "64,45,94,62,63,36,93,58", "MonsterRequiredLetters": {"string": "b"}, "MonsterAllLetters": null, "Stones": {"string": ["n", "b", "x", "b", "b", "t", "t", "b"]}}, {"@SegmentTime": "9", "@spawnIds": "67,74,82,71,70,83,75,66,60", "MonsterRequiredLetters": {"string": "u"}, "MonsterAllLetters": null, "Stones": {"string": ["x", "n", "t", "u", "t", "x", "b", "u", "u"]}}, {"@SegmentTime": "9", "@spawnIds": "64,45,94,62,63,36,93,58", "MonsterRequiredLetters": {"string": "t"}, "MonsterAllLetters": null, "Stones": {"string": ["n", "t", "n", "n", "u", "x", "u", "t"]}}, {"@SegmentTime": "9", "@spawnIds": "67,74,82,71,70,83,75,66,60", "MonsterRequiredLetters": {"string": "b"}, "MonsterAllLetters": null, "Stones": {"string": ["x", "x", "u", "u", "x", "n", "b", "n", "b"]}}]}}}