{"XMLLevel": {"@CollectableMonster": "", "@HideCallout": "2", "@LettersGroup": "4", "@SegmentTime": "10", "@StoneType": "2", "@monsterInputType": "LetterInWord", "Segments": {"Segment": [{"@SegmentTime": "10", "@spawnIds": "54,55,82,83", "MonsterRequiredLetters": {"string": "j"}, "MonsterAllLetters": {"string": ["X", "e", "r", "e"]}, "Stones": {"string": ["o", "z", "ch", "j"]}}, {"@SegmentTime": "10", "@spawnIds": "", "MonsterRequiredLetters": {"string": "k"}, "MonsterAllLetters": {"string": ["X", "o", "l", "e"]}, "Stones": {"string": [{"@spawnId": "54", "#text": "o"}, {"@spawnId": "82", "#text": "o"}, {"@spawnId": "55", "#text": "w"}, {"@spawnId": "83", "#text": "k"}]}}, {"@SegmentTime": "10", "@spawnIds": "0,1,91,92", "MonsterRequiredLetters": {"string": "k"}, "MonsterAllLetters": {"string": ["X", "o", "u", "l", "e"]}, "Stones": {"string": ["j", "w", "k", "k"]}}, {"@SegmentTime": "10", "@spawnIds": "", "MonsterRequiredLetters": {"string": "ch"}, "MonsterAllLetters": {"string": ["X", "a", "c", "h", "e"]}, "Stones": {"string": [{"@spawnId": "0", "#text": "k"}, {"@spawnId": "91", "#text": "w"}, {"@spawnId": "1", "#text": "k"}, {"@spawnId": "92", "#text": "ch"}, {"@spawnId": "26", "#text": "h"}]}}, {"@SegmentTime": "10", "@spawnIds": "94,93,61,59", "MonsterRequiredLetters": {"string": "o"}, "MonsterAllLetters": {"string": ["X", "j", "i", "s"]}, "Stones": {"string": ["k", "z", "k", "o"]}}]}}}