{"XMLLevel": {"@CollectableMonster": "", "@HideCallout": "2", "@LettersGroup": "4", "@SegmentTime": "10", "@StoneType": "2", "@monsterInputType": "LetterInWord", "Segments": {"Segment": [{"@SegmentTime": "10", "@spawnIds": "54,55,82,83", "MonsterRequiredLetters": {"string": "y"}, "MonsterAllLetters": {"string": ["X", "o", "d"]}, "Stones": {"string": ["l", "b", "d", "y"]}}, {"@SegmentTime": "10", "@spawnIds": "", "MonsterRequiredLetters": {"string": "d"}, "MonsterAllLetters": {"string": ["X", "o", "n"]}, "Stones": {"string": [{"@spawnId": "54", "#text": "l"}, {"@spawnId": "82", "#text": "b"}, {"@spawnId": "55", "#text": "l"}, {"@spawnId": "83", "#text": "d"}]}}, {"@SegmentTime": "10", "@spawnIds": "0,1,91,92", "MonsterRequiredLetters": {"string": "y"}, "MonsterAllLetters": {"string": ["X", "o", "d"]}, "Stones": {"string": ["d", "b", "o", "y"]}}, {"@SegmentTime": "10", "@spawnIds": "", "MonsterRequiredLetters": {"string": "d"}, "MonsterAllLetters": {"string": ["X", "o", "l", "a", "b"]}, "Stones": {"string": [{"@spawnId": "0", "#text": "o"}, {"@spawnId": "91", "#text": "n"}, {"@spawnId": "1", "#text": "b"}, {"@spawnId": "92", "#text": "d"}]}}, {"@SegmentTime": "10", "@spawnIds": "94,93,61,59", "MonsterRequiredLetters": {"string": "d"}, "MonsterAllLetters": {"string": ["X", "o", "l", "l", "a", "r"]}, "Stones": {"string": ["d", "n", "y", "d"]}}]}}}