{"XMLLevel": {"@CollectableMonster": "", "@HideCallout": "1", "@LettersGroup": "5", "@SegmentTime": "11", "@StoneType": "1", "@monsterInputType": "Word", "Segments": {"Segment": [{"@SegmentTime": "11", "@spawnIds": "", "MonsterRequiredLetters": {"string": ["\u043c", "\u0438"]}, "MonsterAllLetters": null, "Stones": {"string": [{"@spawnId": "72", "#text": "\u0443"}, {"@spawnId": "81", "#text": "\u0491"}, {"@spawnId": "8", "#text": "\u043b"}, {"@spawnId": "9", "#text": "\u0447"}, {"@spawnId": "69", "#text": "\u043c"}, {"@spawnId": "84", "#text": "\u0438"}]}}, {"@SegmentTime": "11", "@spawnIds": "", "MonsterRequiredLetters": {"string": "\u0437"}, "MonsterAllLetters": null, "Stones": {"string": [{"@spawnId": "1", "#text": "\u0491"}, {"@spawnId": "21", "#text": "\u0447"}, {"@spawnId": "91", "#text": "\u0491"}, {"@spawnId": "85", "#text": "\u044e"}, {"@spawnId": "88", "#text": "\u0447"}, {"@spawnId": "22", "#text": "\u0441"}, {"@spawnId": "92", "#text": "\u0437"}, {"@bonusScore": "275", "@spawnId": "0", "#text": "BonusLetter"}]}}, {"@SegmentTime": "11", "@spawnIds": "", "MonsterRequiredLetters": {"string": ["\u0445", "\u043c", "\u0438", "\u0437"]}, "MonsterAllLetters": null, "Stones": {"string": [{"@spawnId": "72", "#text": "\u044e"}, {"@spawnId": "81", "#text": "\u0447"}, {"@spawnId": "8", "#text": "\u0445"}, {"@spawnId": "9", "#text": "\u043c"}, {"@spawnId": "69", "#text": "\u0438"}, {"@spawnId": "84", "#text": "\u0437"}]}}, {"@SegmentTime": "11", "@spawnIds": "", "MonsterRequiredLetters": {"string": "\u0437"}, "MonsterAllLetters": null, "Stones": {"string": [{"@spawnId": "1", "#text": "\u043b"}, {"@spawnId": "21", "#text": "\u044e"}, {"@spawnId": "91", "#text": "\u0491"}, {"@spawnId": "85", "#text": "\u0447"}, {"@spawnId": "88", "#text": "\u0443"}, {"@spawnId": "22", "#text": "\u0443"}, {"@spawnId": "92", "#text": "\u0437"}, {"@bonusScore": "275", "@spawnId": "0", "#text": "BonusLetter"}]}}, {"@SegmentTime": "11", "@spawnIds": "", "MonsterRequiredLetters": {"string": ["\u0437", "\u0438", "\u043c", "\u0430"]}, "MonsterAllLetters": null, "Stones": {"string": [{"@spawnId": "72", "#text": "\u043b"}, {"@spawnId": "81", "#text": "\u044e"}, {"@spawnId": "8", "#text": "\u0437"}, {"@spawnId": "9", "#text": "\u0438"}, {"@spawnId": "69", "#text": "\u043c"}, {"@spawnId": "84", "#text": "\u0430"}]}}]}}}