{"XMLLevel": {"@CollectableMonster": "", "@HideCallout": "2", "@LettersGroup": "4", "@SegmentTime": "13", "@StoneType": "2", "@monsterInputType": "Word", "Segments": {"Segment": [{"@SegmentTime": "13", "@spawnIds": "56,57,74,75", "MonsterRequiredLetters": {"string": ["v", "\u1ecd", "\u1ecd"]}, "MonsterAllLetters": null, "Stones": {"string": ["n", "v", "\u1ecd", "\u1ecd", {"@bonusScore": "275", "@spawnId": "60", "#text": "BonusLetter"}]}}, {"@SegmentTime": "13", "@spawnIds": "28,78,79,36,45", "MonsterRequiredLetters": {"string": ["y", "\u1ecd", "t", "a"]}, "MonsterAllLetters": null, "Stones": {"string": ["b", "y", "\u1ecd", "t", "a", {"@spawnId": "25", "#text": "MagnetLetter"}]}}, {"@SegmentTime": "13", "@spawnIds": "11,12,89,90,60", "MonsterRequiredLetters": {"string": ["a", "t", "\u1ecd"]}, "MonsterAllLetters": null, "Stones": {"string": ["w", "z", "a", "t", "\u1ecd"]}}, {"@SegmentTime": "13", "@spawnIds": "20,75,74,0,1", "MonsterRequiredLetters": {"string": ["v", "\u1ecd", "\u1ecd"]}, "MonsterAllLetters": null, "Stones": {"string": ["n", "n", "v", "\u1ecd", "\u1ecd", {"@bonusScore": "275", "@spawnId": "23", "#text": "BonusLetter"}]}}, {"@SegmentTime": "13", "@spawnIds": "95,96,8,9,26", "MonsterRequiredLetters": {"string": ["u", "z", "\u1ecd"]}, "MonsterAllLetters": null, "Stones": {"string": ["t", "n", "u", "z", "\u1ecd", {"@spawnId": "27", "#text": "MagnetLetter"}]}}]}}}