<XMLLevel CollectableMonster="" HideCallout="-1" LettersGroup="17" SegmentTime="11" StoneType="1" monsterInputType="Letter">
  <Segments>
  		<Segment SegmentTime="10" spawnIds="">
		
      	<MonsterRequiredLetters>
			<string>గం</string>
	  	</MonsterRequiredLetters>
	  	<MonsterAllLetters>
	  	</MonsterAllLetters>
	  	<Stones>
			<string spawnId="10">ణం</string>
	        <string spawnId="61">ఞౌ</string>
			<string spawnId="71">ఖం</string>

			<string spawnId="96">గం</string>
			<string spawnId="13">గం</string>
			<string spawnId="95">హం</string>
			<string spawnId="55">దః</string>
			<string spawnId="70">ధః</string>
      	</Stones>
	</Segment>
    <Segment SegmentTime="10" spawnIds="">
    	
    	<MonsterRequiredLetters>
    		<string>ఖః</string>
    	</MonsterRequiredLetters>
    	<MonsterAllLetters>
    	</MonsterAllLetters>
    	<Stones>
    		<string spawnId="87">ధం</string>
			<string spawnId="78">సః</string>
    		<string spawnId="64">హౌ</string>
			<string spawnId="60">దః</string>
			<string spawnId="36">ధం</string>
			<string spawnId="79">ఖః</string>
			<string spawnId="86">దం</string>

			<string spawnId="45">సం</string>
    	</Stones>
	</Segment>
	<Segment SegmentTime="10" spawnIds="">
		
      	<MonsterRequiredLetters>
			<string>దః</string>
	  	</MonsterRequiredLetters>
	  	<MonsterAllLetters>
	  	</MonsterAllLetters>
	  	<Stones>
	        <string spawnId="20">సం</string>
			<string spawnId="23">ధః</string>
			<string spawnId="54">యః</string>
			<string spawnId="55">సౌ</string>
			<string spawnId="58">దః</string>

			<string spawnId="21">Shield</string>

      	</Stones>
    </Segment>
	<Segment SegmentTime="10" spawnIds="">
		
		<MonsterRequiredLetters>
			<string>ఖం</string>
		</MonsterRequiredLetters>
	  	<MonsterAllLetters>
	  	</MonsterAllLetters>
	  	<Stones>
        	<string spawnId="18">సం</string>
			<string spawnId="19">ఖం</string>
			<string spawnId="36">టం</string>
			<string spawnId="45">ణః</string>
			<string spawnId="57">జౌ</string>
			<string spawnId="56">దౌ</string>

			<string bonusScore="275" spawnId="9">BonusLetter</string>
      	</Stones>
    </Segment>


	<Segment SegmentTime="10" spawnIds="87,78,64,60,36,79,86,63,45">
		
      	<MonsterRequiredLetters>
			<string>హం</string>
	  	</MonsterRequiredLetters>
	  	<MonsterAllLetters>
	  	</MonsterAllLetters>
	  	<Stones>
	        <string>టః</string>
			<string>ణం</string>
			<string>యః</string>
			<string>ణః</string>
			<string>జః</string>
			<string>ధః</string>
			<string>ధం</string>
			<string>హం</string>
			<string>ఞం</string>
      	</Stones>
	</Segment>
  </Segments>
</XMLLevel>