{"XMLLevel": {"@CollectableMonster": "", "@HideCallout": "2", "@LettersGroup": "4", "@SegmentTime": "9", "@StoneType": "1", "@monsterInputType": "LetterInWord", "Segments": {"Segment": [{"@SegmentTime": "10", "@spawnIds": "5,4,74,75,56,57,87,86,60", "MonsterRequiredLetters": {"string": "v"}, "MonsterAllLetters": {"string": ["X", "o", "w", "a"]}, "Stones": {"string": ["o", "e", "r", "k", "r", "e", "w", "r", "v"]}}, {"@SegmentTime": "10", "@spawnIds": "5,4,74,75,56,57,87,86,60", "MonsterRequiredLetters": {"string": "o"}, "MonsterAllLetters": {"string": ["X", "\u1e71", "h", "e"]}, "Stones": {"string": [{"@spawnId": "11", "#text": "o"}, {"@spawnId": "15", "#text": "e"}, {"@spawnId": "19", "#text": "r"}, {"@spawnId": "12", "#text": "v"}, {"@spawnId": "14", "#text": "k"}, {"@spawnId": "18", "#text": "o"}, {"@spawnId": "21", "#text": "e"}, {"@spawnId": "22", "#text": "o"}, {"@spawnId": "26", "#text": "o"}]}}, {"@SegmentTime": "10", "@spawnIds": "5,4,74,75,56,57,87,86,60", "MonsterRequiredLetters": {"string": "w"}, "MonsterAllLetters": {"string": ["X", "o", "\u1e71", "h", "e"]}, "Stones": {"string": ["w", "v", "t", "r", "e", "r", "r", "v", "w"]}}, {"@SegmentTime": "10", "@spawnIds": "5,4,74,75,56,57,87,86,60", "MonsterRequiredLetters": {"string": "w"}, "MonsterAllLetters": {"string": ["X", "o", "\u1e71", "h", "e"]}, "Stones": {"string": [{"@spawnId": "20", "#text": "o"}, {"@spawnId": "33", "#text": "t"}, {"@spawnId": "23", "#text": "v"}, {"@spawnId": "28", "#text": "e"}, {"@spawnId": "25", "#text": "e"}, {"@spawnId": "32", "#text": "t"}, {"@spawnId": "21", "#text": "o"}, {"@spawnId": "22", "#text": "v"}, {"@spawnId": "12", "#text": "w"}]}}, {"@SegmentTime": "10", "@spawnIds": "5,4,74,75,56,57,87,86,60", "MonsterRequiredLetters": {"string": "r"}, "MonsterAllLetters": {"string": ["X", "o", "v", "h", "a"]}, "Stones": {"string": ["t", "o", "r", "o", "o", "o", "t", "o", "r"]}}]}}}