{"XMLLevel": {"@CollectableMonster": "", "@HideCallout": "4", "@LettersGroup": "3", "@SegmentTime": "10", "@StoneType": "1", "@monsterInputType": "LetterInWord", "Segments": {"Segment": [{"@SegmentTime": "10", "@spawnIds": "59,64,78,17,16,79,63,61", "MonsterRequiredLetters": {"string": "s"}, "MonsterAllLetters": {"string": ["X", "i", "s", "i", "w"]}, "Stones": {"string": ["b", "w", "b", "i", "b", "i", "b", "s"]}}, {"@SegmentTime": "10", "@spawnIds": "59,64,78,17,16,79,63,61", "MonsterRequiredLetters": {"string": "s"}, "MonsterAllLetters": {"string": ["X", "i", "s", "i", "w"]}, "Stones": {"string": ["b", "s", "i", "s", "b", "i", "s", "s"]}}, {"@SegmentTime": "10", "@spawnIds": "", "MonsterRequiredLetters": {"string": "b"}, "MonsterAllLetters": {"string": ["X", "i", "b", "i"]}, "Stones": {"string": [{"@spawnId": "69", "#text": "i"}, {"@spawnId": "84", "#text": "w"}, {"@delayIn": "0", "@delayRepet": "0", "@loop": "true", "@spawnId": "11,86,11", "@speed": "150", "#text": "w"}, {"@spawnId": "81", "#text": "i"}, {"@delayIn": "0", "@delayRepet": "0", "@loop": "true", "@spawnId": "87,12,87", "@speed": "150", "#text": "s"}, {"@spawnId": "72", "#text": "w"}, {"@spawnId": "19", "#text": "b"}, {"@bonusScore": "275", "@spawnId": "18", "#text": "BonusLetter"}]}}, {"@SegmentTime": "10", "@spawnIds": "59,64,78,17,16,79,63,61", "MonsterRequiredLetters": {"string": "b"}, "MonsterAllLetters": {"string": ["X", "i", "b", "i"]}, "Stones": {"string": ["i", "w", "s", "b", "s", "i", "i", "b"]}}, {"@SegmentTime": "10", "@spawnIds": "59,64,78,17,16,79,63,61", "MonsterRequiredLetters": {"string": "b"}, "MonsterAllLetters": {"string": ["X", "i", "b", "i"]}, "Stones": {"string": ["b", "i", "b", "b", "b", "i", "s", "b"]}}]}}}