{"XMLLevel": {"@CollectableMonster": "", "@HideCallout": "1", "@LettersGroup": "5", "@SegmentTime": "9", "@StoneType": "1", "@monsterInputType": "LetterInWord", "Segments": {"Segment": [{"@SegmentTime": "9", "@spawnIds": "", "MonsterRequiredLetters": {"string": "u"}, "MonsterAllLetters": {"string": ["X", "g"]}, "Stones": {"string": [{"@spawnId": "4", "#text": "g"}, {"@spawnId": "74", "#text": "p"}, {"@spawnId": "87", "#text": "ng"}, {"@spawnId": "23", "#text": "p"}, {"@spawnId": "60", "#text": "ng"}, {"@spawnId": "5", "#text": "p"}, {"@spawnId": "86", "#text": "g"}, {"@spawnId": "20", "#text": "g"}, {"@spawnId": "75", "#text": "u"}]}}, {"@SegmentTime": "9", "@spawnIds": "", "MonsterRequiredLetters": {"string": "p"}, "MonsterAllLetters": {"string": ["X", "u", "n", "g"]}, "Stones": {"string": [{"@spawnId": "71", "#text": "ng"}, {"@spawnId": "70", "#text": "g"}, {"@spawnId": "76", "#text": "g"}, {"@spawnId": "88", "#text": "ng"}, {"@spawnId": "21", "#text": "u"}, {"@spawnId": "3", "#text": "u"}, {"@spawnId": "85", "#text": "p"}, {"@spawnId": "22", "#text": "u"}, {"@spawnId": "73", "#text": "p"}, {"@spawnId": "2", "#text": "p"}]}}, {"@SegmentTime": "9", "@spawnIds": "4,74,87,23,60,5,86,20,75", "MonsterRequiredLetters": {"string": "u"}, "MonsterAllLetters": {"string": ["X", "p"]}, "Stones": {"string": ["g", "g", "p", "p", "ng", "p", "g", "g", "u"]}}, {"@SegmentTime": "9", "@spawnIds": "4,74,87,23,60,5,86,20,75", "MonsterRequiredLetters": {"string": "u"}, "MonsterAllLetters": {"string": ["X", "g"]}, "Stones": {"string": ["g", "ng", "ng", "g", "ng", "p", "g", "p", "u"]}}, {"@SegmentTime": "9", "@spawnIds": "", "MonsterRequiredLetters": {"string": "u"}, "MonsterAllLetters": {"string": ["X", "p"]}, "Stones": {"string": [{"@spawnId": "71", "#text": "ng"}, {"@spawnId": "70", "#text": "ng"}, {"@spawnId": "76", "#text": "u"}, {"@spawnId": "88", "#text": "g"}, {"@spawnId": "21", "#text": "ng"}, {"@spawnId": "3", "#text": "ng"}, {"@spawnId": "85", "#text": "u"}, {"@spawnId": "22", "#text": "p"}, {"@spawnId": "73", "#text": "p"}, {"@spawnId": "2", "#text": "u"}]}}]}}}