{"XMLLevel": {"@CollectableMonster": "", "@HideCallout": "-1", "@LettersGroup": "6", "@SegmentTime": "11", "@StoneType": "1", "@monsterInputType": "Letter", "Segments": {"Segment": [{"@SegmentTime": "11", "@spawnIds": "", "MonsterRequiredLetters": {"string": "127"}, "MonsterAllLetters": null, "Stones": {"string": [{"@spawnId": "84", "#text": "110"}, {"@spawnId": "54", "#text": "4"}, {"@spawnId": "55", "#text": "124"}, {"@spawnId": "81", "#text": "127"}]}}, {"@SegmentTime": "11", "@spawnIds": "", "MonsterRequiredLetters": {"string": "134"}, "MonsterAllLetters": null, "Stones": {"string": [{"@spawnId": "82", "#text": "150"}, {"@spawnId": "8", "#text": "134"}, {"@spawnId": "83", "#text": "155"}, {"@spawnId": "9", "#text": "78"}]}}, {"@SegmentTime": "11", "@spawnIds": "", "MonsterRequiredLetters": {"string": "128"}, "MonsterAllLetters": null, "Stones": {"string": [{"@spawnId": "3", "#text": "4"}, {"@spawnId": "70", "#text": "11"}, {"@spawnId": "71", "#text": "136"}, {"@spawnId": "2", "#text": "128"}]}}, {"@SegmentTime": "11", "@spawnIds": "", "MonsterRequiredLetters": {"string": "155"}, "MonsterAllLetters": null, "Stones": {"string": [{"@spawnId": "23", "#text": "115"}, {"@spawnId": "74", "#text": "136"}, {"@spawnId": "75", "#text": "155"}, {"@spawnId": "20", "#text": "157"}]}}, {"@SegmentTime": "11", "@spawnIds": "", "MonsterRequiredLetters": {"string": "76"}, "MonsterAllLetters": null, "Stones": {"string": [{"@spawnId": "89", "#text": "124"}, {"@spawnId": "96", "#text": "131"}, {"@spawnId": "95", "#text": "141"}, {"@spawnId": "90", "#text": "76"}, {"@bonusScore": "125", "@spawnId": "18", "#text": "BonusLetter"}, {"@bonusScore": "125", "@spawnId": "19", "#text": "BonusLetter"}]}}]}}}