{"XMLLevel": {"@CollectableMonster": "", "@HideCallout": "2", "@LettersGroup": "4", "@SegmentTime": "13", "@StoneType": "2", "@monsterInputType": "Word", "Segments": {"Segment": [{"@SegmentTime": "13", "@spawnIds": "56,57,74,75", "MonsterRequiredLetters": {"string": ["c", "u", "n"]}, "MonsterAllLetters": null, "Stones": {"string": ["k", "c", "u", "n", {"@bonusScore": "275", "@spawnId": "60", "#text": "BonusLetter"}]}}, {"@SegmentTime": "13", "@spawnIds": "28,78,79,36,45", "MonsterRequiredLetters": {"string": ["q", "u", "f", "u", "l"]}, "MonsterAllLetters": null, "Stones": {"string": ["q", "u", "f", "u", "l", {"@spawnId": "25", "#text": "MagnetLetter"}]}}, {"@SegmentTime": "13", "@spawnIds": "11,12,89,90,60", "MonsterRequiredLetters": {"string": ["d", "u", "n"]}, "MonsterAllLetters": null, "Stones": {"string": ["q", "sh", "d", "u", "n"]}}, {"@SegmentTime": "13", "@spawnIds": "20,75,74,0,1", "MonsterRequiredLetters": {"string": ["d", "u", "n"]}, "MonsterAllLetters": null, "Stones": {"string": ["c", "k", "d", "u", "n", {"@bonusScore": "275", "@spawnId": "23", "#text": "BonusLetter"}]}}, {"@SegmentTime": "13", "@spawnIds": "95,96,8,9,26", "MonsterRequiredLetters": {"string": ["u", "b", "a", "x"]}, "MonsterAllLetters": null, "Stones": {"string": ["k", "u", "b", "a", "x", {"@spawnId": "27", "#text": "MagnetLetter"}]}}]}}}