{"XMLLevel": {"@CollectableMonster": "", "@HideCallout": "-1", "@LettersGroup": "1", "@SegmentTime": "14", "@StoneType": "1", "@monsterInputType": "Word", "Segments": {"Segment": [{"@SegmentTime": "14", "@spawnIds": "", "MonsterRequiredLetters": {"string": ["a", "w", "a"]}, "MonsterAllLetters": null, "Stones": {"string": [{"@spawnId": "21", "#text": "a"}, {"@spawnId": "60", "#text": "w"}, {"@spawnId": "22", "#text": "a"}]}}, {"@SegmentTime": "14", "@spawnIds": "", "MonsterRequiredLetters": {"string": ["a", "w", "a"]}, "MonsterAllLetters": null, "Stones": {"string": [{"@spawnId": "58", "#text": "a"}, {"@spawnId": "93", "#text": "w"}, {"@spawnId": "36", "#text": "a"}]}}, {"@SegmentTime": "14", "@spawnIds": "", "MonsterRequiredLetters": {"string": ["a", "w", "o"]}, "MonsterAllLetters": null, "Stones": {"string": [{"@spawnId": "45", "#text": "a"}, {"@spawnId": "94", "#text": "w"}, {"@spawnId": "62", "#text": "o"}]}}, {"@SegmentTime": "14", "@spawnIds": "", "MonsterRequiredLetters": {"string": ["a", "w", "o"]}, "MonsterAllLetters": null, "Stones": {"string": [{"@spawnId": "26", "#text": "a"}, {"@spawnId": "8", "#text": "w"}, {"@spawnId": "9", "#text": "o"}, {"@bonusScore": "175", "@spawnId": "27", "#text": "BonusLetter"}]}}, {"@SegmentTime": "14", "@spawnIds": "", "MonsterRequiredLetters": {"string": ["a", "w", "o"]}, "MonsterAllLetters": null, "Stones": {"string": [{"@spawnId": "26", "#text": "a"}, {"@spawnId": "8", "#text": "w"}, {"@spawnId": "9", "#text": "o"}, {"@spawnId": "27", "#text": "MagnetLetter"}]}}]}}}